Workbook

Sheet Audit Leads
A1: Timestamp | B1: Email address | C1: Full name | D1: Work email | E1: Contact No | F1: Your Role in Business | G1: Company name | H1: Website(Optional) | I1: Industry | J1: Company size | K1: Monthly revenue | L1: Country | M1: Tools you currently use | N1: How does your operation run today? (Describe your team, processes, and handoffs..) | O1: Where is the biggest pain? (pick all that apply) | P1: Estimated hours lost per week to manual work | Q1: Your team's AI experience | R1: Existing automations (Zapier, scripts, etc.) | S1: Data readiness | T1: Which workflows would you like AI to handle? (Be specific — e.g., 'classify inbound emails, draft replies, sync to CRM') | U1: Desired outcomes | V1: Timeline | W1: Budget | X1: Decision authority | Y1: Anything else we should know? (Constraints, integrations, security needs...) | Z1: How did you hear about us? (Mention your referral in others) | AA1: Upload any helpful files such as workflow screenshots, Excel sheets, SOPs, reports, CRM exports, invoice samples, lead sheets, process documents, or project requirements. | AB1: I agree that AKcelerateHQ may contact me regarding my automation audit request. | AC1: processed | AD1: status | AE1: audit_score | AF1: lead_category | AG1: priority_reason | AH1: recommended_offer | AI1: next_action | AJ1: assigned_owner | AK1: call_status | AL1: proposal_status | AM1: n8n_sent | AN1: n8n_response | AO1: notes | AP1: updated_at | AQ1: row_number
AC2: {=IF(B2:B101="", "", XLOOKUP(B2:B101, 'Audit Leads'!C2:C101, 'Audit Leads'!AD2:AQ101, ""))} | AQ2: {=IF(A2:A101<>"", ROW(A2:A101)-1, "")}

Sheet Automation Opportunities
A1: opportunity_id | B1: company_name | C1: pain_area | D1: recommended_workflow | E1: manual_hours_weekly | F1: estimated_monthly_value_usd | G1: complexity | H1: suggested_price_range | I1: priority | J1: owner | K1: status | L1: notes
A2: OPP-001 | B2: Shah Distributors | C2: Lead qualification + CRM follow-up | D2: WhatsApp lead capture, AI score, CRM sync, owner dashboard | E2: 70 | F2: 3031 | G2: Medium | H2: $2,000 – $6,000 | I2: High | J2: Kalpesh | K2: Demo Needed | L2: Use this row as n8n-generated opportunity example.
A3: OPP-002 | B3: BrightFuture Classes | C3: Admission lead conversion | D3: Inquiry qualification, WhatsApp follow-ups, demo class booking, admission dashboard | E3: 25 | F3: 1083 | G3: Medium | H3: $1,000 – $2,000 | I3: Medium | J3: Kalpesh | K3: Nurture
A4: OPP-003 | B4: UrbanCare Clinic | C4: Document + approval workflow | D4: Patient request triage, approval routing, report summary, audit logs | E4: 120 | F4: 5196 | G4: High | H4: $6,000+ | I4: High | J4: Kalpesh | K4: Discovery Needed | L4: Security requirement.
A5: OPP-004 | B5: CraftNest Store | C5: Customer support + reporting | D5: AI support drafts, customer segmentation, weekly Shopify report | E5: 10 | F5: 433 | G5: Low | H5: $300 – $1,000 | I5: Low | J5: Kalpesh | K5: Nurture
A6: OPP-005 | B6: SideProject AI | C6: Cold outreach CRM | D6: Simple lead list, cold email drafting, CRM update | E6: 3 | F6: 130 | G6: Low | H6: Less than $300 | I6: Low | J6: Kalpesh | K6: Nurture

Sheet Scoring Criteria
A1: Dimension | B1: How it is scored | C1: Max Points | D1: Sheet Column | E1: Why it matters
A2: Automation Fit | B2: Strong pain match: data entry, reporting, lead qualification, docs, approvals, search | C2: 15 | D2: AH | E2: Shows whether automation can create visible ROI.
A3: Pain Severity | B3: Mapped from hours lost per week | C3: 25 | D3: AI | E3: More hours lost means stronger business case.
A4: Urgency | B4: ASAP = highest, exploring = lowest | C4: 20 | D4: AJ | E4: Urgency tells how fast to follow up.
A5: Budget | B5: Higher budget = higher fit; not sure still gets medium score | C5: 25 | D5: AK | E5: Helps route to starter vs scale offer.
A6: Authority | B6: Decision maker = highest | C6: 20 | D6: AL | E6: Avoids wasting calls with non-buyers.
A7: Data Readiness | B7: CRM/database/warehouse/pipelines score higher than spreadsheets only | C7: 20 | D7: AM | E7: Cleaner data usually means faster implementation.
A8: Revenue Fit | B8: Larger revenue bands score higher | C8: 22 | D8: AN | E8: Indicates ability to pay and scale.
A9: Specific Workflow Detail | B9: Extra 10 points if workflow request is detailed | C9: 10 | D9: T | E9: Detailed problem = easier proposal.
A10: Consent | B10: 3 points if consent is Yes | C10: 3 | D10: AB | E10: Confirms contact permission.
A11: Lead Score | B11: MIN(100, all score dimensions) | C11: 100 | D11: AF | E11: Used for Hot/Warm/Cold classification.

Sheet Routing Rules
A1: Condition | B1: Lead Label | C1: Recommended Action | D1: Owner | E1: SLA | F1: n8n Routing Note
A2: lead_score >= 75 AND budget is $2,000+ | B2: Hot | C2: Send WhatsApp, email summary, and book discovery call | D2: Founder | E2: 24 hours | F2: Create high-priority task + send owner alert
A3: lead_score 50-74 | B3: Warm | C3: Send personalized audit summary + 2 questions | D3: Founder/Assistant | E3: 48 hours | F3: Create nurture sequence
A4: lead_score 30-49 | B4: Cold | C4: Send useful audit result + case study | D4: Assistant | E4: 3-5 days | F4: Add to nurture list
A5: timeline is Just exploring OR budget < $300 | B5: Nurture | C5: Send starter resource and follow-up later | D5: Assistant | E5: 7-14 days | F5: No sales call unless they reply
A6: consent != Yes | B6: Do Not Contact | C6: Do not send outreach | D6: System | E6: Immediate | F6: Stop automation for that row

Sheet Discovery Slots
A1: slot_id | B1: date | C1: start_time | D1: end_time | E1: timezone | F1: available | G1: booked_by | H1: calendar_event_id | I1: google_meet_link | J1: notes
A2: SLOT-001 | B2: 2026-06-28 | C2: 11:00 | D2: 11:30 | E2: Asia/Kolkata | F2: Yes
A3: SLOT-002 | B3: 2026-06-28 | C3: 16:00 | D3: 16:30 | E3: Asia/Kolkata | F3: Yes
A4: SLOT-003 | B4: 2026-06-29 | C4: 11:00 | D4: 11:30 | E4: Asia/Kolkata | F4: Yes
A5: SLOT-004 | B5: 2026-06-29 | C5: 16:00 | D5: 16:30 | E5: Asia/Kolkata | F5: Yes
A6: SLOT-005 | B6: 2026-06-30 | C6: 11:00 | D6: 11:30 | E6: Asia/Kolkata | F6: Yes
A7: SLOT-006 | B7: 2026-06-30 | C7: 16:00 | D7: 16:30 | E7: Asia/Kolkata | F7: Yes
A8: SLOT-007 | B8: 2026-07-01 | C8: 11:00 | D8: 11:30 | E8: Asia/Kolkata | F8: Yes
A9: SLOT-008 | B9: 2026-07-01 | C9: 16:00 | D9: 16:30 | E9: Asia/Kolkata | F9: Yes
A10: SLOT-009 | B10: 2026-07-02 | C10: 11:00 | D10: 11:30 | E10: Asia/Kolkata | F10: Yes
A11: SLOT-010 | B11: 2026-07-02 | C11: 16:00 | D11: 16:30 | E11: Asia/Kolkata | F11: Yes
A12: SLOT-011 | B12: 2026-07-03 | C12: 11:00 | D12: 11:30 | E12: Asia/Kolkata | F12: Yes
A13: SLOT-012 | B13: 2026-07-03 | C13: 16:00 | D13: 16:30 | E13: Asia/Kolkata | F13: Yes
... A15: SLOT-014 | B15: 2026-07-04 | C15: 16:00 | D15: 16:30 | E15: Asia/Kolkata | F15: Yes

Sheet Dashboard
A1: AKcelerateHQ Automation Audit Dashboard
A3: Metric | B3: Value | D3: Status | E3: Count | G3: Lead Temperature | H3: Count
A4: Total Audit Leads | B4: =COUNTA('Audit Leads'!C2:C201) -> 1 | D4: New | E4: =COUNTIF('Audit Leads'!AE2:AE201,D4) -> #REF! | G4: Hot | H4: =COUNTIF('Audit Leads'!AG2:AG201,G4) -> #REF!
A5: Hot Leads | B5: =COUNTIF('Audit Leads'!AG2:AG201,"Hot") -> #REF! | D5: Scored | E5: =COUNTIF('Audit Leads'!AE2:AE201,D5) -> #REF! | G5: Warm | H5: =COUNTIF('Audit Leads'!AG2:AG201,G5) -> #REF!
A6: Warm Leads | B6: =COUNTIF('Audit Leads'!AG2:AG201,"Warm") -> #REF! | D6: Contacted | E6: =COUNTIF('Audit Leads'!AE2:AE201,D6) -> #REF! | G6: Cold | H6: =COUNTIF('Audit Leads'!AG2:AG201,G6) -> #REF!
A7: Discovery Scheduled | B7: =COUNTIF('Audit Leads'!AE2:AE201,"Discovery Scheduled") -> #REF! | D7: Discovery Scheduled | E7: =COUNTIF('Audit Leads'!AE2:AE201,D7) -> #REF! | G7: Low Fit | H7: =COUNTIF('Audit Leads'!AG2:AG201,G7) -> #REF!
A8: Proposal Sent | B8: =COUNTIF('Audit Leads'!AE2:AE201,"Proposal Sent") -> #REF! | D8: Proposal Sent | E8: =COUNTIF('Audit Leads'!AE2:AE201,D8) -> #REF!
A9: Won | B9: =COUNTIF('Audit Leads'!AE2:AE201,"Won") -> #REF! | D9: Won | E9: =COUNTIF('Audit Leads'!AE2:AE201,D9) -> #REF!
A10: Lost | B10: =COUNTIF('Audit Leads'!AE2:AE201,"Lost") -> #REF! | D10: Lost | E10: =COUNTIF('Audit Leads'!AE2:AE201,D10) -> #REF!
A11: Avg Lead Score | B11: =IFERROR(ROUND(AVERAGEIF('Audit Leads'!AF2:AF201,">0",'Audit Leads'!AF2:AF201),0),0) -> 0 | D11: Nurture | E11: =COUNTIF('Audit Leads'!AE2:AE201,D11) -> #REF!
A14: Top Pain Areas | B14: Count | C14: What to pitch | E14: Budget Segment | F14: Count | G14: Timeline | H14: Count
A15: Manual data entry | B15: =SUMPRODUCT(--ISNUMBER(SEARCH("Manual data entry",'Audit Leads'!P2:P201))) -> 0 | C15: AI data capture + sheet/CRM sync | E15: Less than $300 | F15: =COUNTIF('Audit Leads'!X2:X201,"Less than $300") -> #REF! | G15: ASAP (< 21 days) | H15: =COUNTIF('Audit Leads'!W2:W201,"ASAP (< 21 days)") -> #REF!
A16: Lead qualification overhead | B16: =SUMPRODUCT(--ISNUMBER(SEARCH("Lead qualification",'Audit Leads'!P2:P201))) -> 0 | C16: Lead scoring + WhatsApp follow-up | E16: $300 – $1,000 | F16: =COUNTIF('Audit Leads'!X2:X201,"$300 – $1,000") -> #REF! | G16: 1-3 months | H16: =COUNTIF('Audit Leads'!W2:W201,"1-3 months") -> #REF!
A17: Slow customer support | B17: =SUMPRODUCT(--ISNUMBER(SEARCH("Slow customer support",'Audit Leads'!P2:P201))) -> 0 | C17: AI inbox/support triage | E17: $1,000 – $2,000 | F17: =COUNTIF('Audit Leads'!X2:X201,"$1,000 – $2,000") -> #REF! | G17: Flexible | H17: =COUNTIF('Audit Leads'!W2:W201,"We are Flexible at timeline") -> #REF!
A18: Repetitive reporting | B18: =SUMPRODUCT(--ISNUMBER(SEARCH("Repetitive reporting",'Audit Leads'!P2:P201))) -> 0 | C18: Owner dashboard + scheduled report | E18: $2,000 – $6,000 | F18: =COUNTIF('Audit Leads'!X2:X201,"$2,000 – $6,000") -> #REF! | G18: Just exploring | H18: =COUNTIF('Audit Leads'!W2:W201,"Just exploring") -> #REF!
A19: Document processing | B19: =SUMPRODUCT(--ISNUMBER(SEARCH("Document processing",'Audit Leads'!P2:P201))) -> 0 | C19: Document extraction + approval flow | E19: $6,000+ | F19: =COUNTIF('Audit Leads'!X2:X201,"$6,000+") -> #REF! | G19: Other | H19: =COUNTIF('Audit Leads'!W2:W201,"Other:") -> #REF!
A20: Inventory / supply chain | B20: =SUMPRODUCT(--ISNUMBER(SEARCH("Inventory",'Audit Leads'!P2:P201))) -> 0 | C20: Inventory dashboard + alerts

Sheet Lookups
A1: category | B1: value
A2: Status | B2: New
A3: Status | B3: Scored
A4: Status | B4: Contacted
A5: Status | B5: Discovery Scheduled
A6: Status | B6: Discovery Done
A7: Status | B7: Proposal Pending
A8: Status | B8: Proposal Sent
A9: Status | B9: Won
A10: Status | B10: Lost
A11: Status | B11: Nurture
A12: Status | B12: On Hold
... A131: Recommended Offer | B131: Maintenance + Optimization

Sheet Setup
A1: AKcelerateHQ Audit Form Setup
A2: Form Edit URL | B2: https://docs.google.com/forms/d/YOUR_GOOGLE_FORM_ID/edit
A3: Form Public URL | B3: https://docs.google.com/forms/d/e/YOUR_GOOGLE_FORM_ID/viewform
A4: Spreadsheet ID | B4: YOUR_GOOGLE_SHEET_ID
A5: n8n Webhook URL | B5: Add webhook in CONFIG.N8N_WEBHOOK_URL
A6: Brand Theme | B6: Navy #102040 | Deep Blue #0458D6 | Azure #0880D8 | Cyan #35BAE0

Sheet README
A1: AKcelerateHQ Automation Audit CRM - README
A3: Use this workbook as the Google Sheet backend for the AKcelerateHQ Audit Form.
A5: Recommended flow
A6: Google Form → linked response sheet → Apps Script column mapper → Audit Leads tab → n8n webhook → AI scoring / WhatsApp / email / CRM updates
A8: Main n8n tab
A9: Audit Leads
A11: Important columns
A12: processed, status, priority, lead_score, lead_temperature, recommended_offer, recommended_workflow, recommended_action, whatsapp_status, proposal_status
A14: How to use
A15: 1. Upload this .xlsx to Google Drive and open with Google Sheets.
A16: 2. Create / connect your Google Form responses.
A17: 3. Map form responses into the Audit Leads tab using Apps Script or n8n.
... A25: Styled with AKcelerateHQ colors: Navy #102040, Blue #0458D6, Cyan #35BAE0, Soft White #F1F0EE.
